enconv/__init__.py
enconv/encheck.py
enconv/encoding_converter.py
enconv/enconv.py
enconv/enportal.py
enconv-0.0.5.data/scripts/encheck
enconv-0.0.5.data/scripts/enconv
enconv-0.0.5.data/scripts/enportal
enconv-0.0.5.dist-info/LICENSE
enconv-0.0.5.dist-info/METADATA
enconv-0.0.5.dist-info/WHEEL
enconv-0.0.5.dist-info/top_level.txt
enconv-0.0.5.dist-info/RECORD
