Metadata-Version: 2.1
Name: enconv
Version: 0.0.5
Summary: Encoding conversion utilities based on chardet.
Home-page: https://github.com/joy13975/enconv
Author: Joy Yeh
Author-email: joyyeh.tw@gmail.com
Classifier: Programming Language :: Python :: 3
Classifier: License :: OSI Approved :: MIT License
Classifier: Operating System :: OS Independent
Requires-Python: >=3.6
License-File: LICENSE
Requires-Dist: chardet ==3.0.4
